uv_sbom_bin/__init__.py
uv_sbom_bin/__main__.py
uv_sbom_bin/install.py
uv_sbom_bin-1.0.0.dist-info/METADATA
uv_sbom_bin-1.0.0.dist-info/WHEEL
uv_sbom_bin-1.0.0.dist-info/entry_points.txt
uv_sbom_bin-1.0.0.dist-info/RECORD
