Metadata-Version: 2.4
Name: uv-sbom-bin
Version: 1.0.0
Summary: Python wrapper for uv-sbom - SBOM generation tool for uv projects
Project-URL: Homepage, https://github.com/Taketo-Yoda/uv-sbom
Project-URL: Repository, https://github.com/Taketo-Yoda/uv-sbom
Project-URL: Bug Tracker, https://github.com/Taketo-Yoda/uv-sbom/issues
Author-email: Taketo Yoda <exhaust7.drs@gmail.com>
License: MIT
Keywords: cyclonedx,python-wrapper,sbom,security,supply-chain,uv
Classifier: Development Status :: 5 - Production/Stable
Classifier: Intended Audience :: Developers
Classifier: License :: OSI Approved :: MIT License
Classifier: Operating System :: OS Independent
Classifier: Programming Language :: Python :: 3
Classifier: Programming Language :: Python :: 3.8
Classifier: Programming Language :: Python :: 3.9
Classifier: Programming Language :: Python :: 3.10
Classifier: Programming Language :: Python :: 3.11
Classifier: Programming Language :: Python :: 3.12
Classifier: Topic :: Security
Classifier: Topic :: Software Development :: Build Tools
Classifier: Topic :: System :: Software Distribution
Requires-Python: >=3.8
